miss/MissingData.py
missing_3327-1.0.0.dist-info/LICENSE
missing_3327-1.0.0.dist-info/LICENSE.py
missing_3327-1.0.0.dist-info/METADATA
missing_3327-1.0.0.dist-info/WHEEL
missing_3327-1.0.0.dist-info/entry_points.txt
missing_3327-1.0.0.dist-info/top_level.txt
missing_3327-1.0.0.dist-info/RECORD
